{"is_source_file": false, "format": "", "description": "", "external_files": [], "external_methods": [], "published": [], "classes": [], "methods": [], "calls": [], "search-terms": [], "state": 2, "file_id": 4, "knowledge_revision": 16, "git_revision": "e59c51f30c3adbb1cd33d117f4ab931754da5820", "hash": "22f9e17cc1848b56dbb244518ac2707e", "format-version": 4, "code-base-name": "patient_portal_frontend", "filename": "patient_portal_frontend/src/App.css", "revision_history": [{"16": "e59c51f30c3adbb1cd33d117f4ab931754da5820"}]}